ndd_tools/__init__.py
ndd_tools/api_client.py
ndd_tools/boring_regex.py
ndd_tools/constants.py
ndd_tools/data_model_validators.py
ndd_tools/data_models.py
ndd_tools/datetime_converter.py
ndd_tools/logger_mixin.py
ndd_tools/others.py
ndd_tools/regex_executor.py
ndd_tools/schemas.py
ndd_tools/threading_woker.py
ndd_tools/utils.py
ndd_tools/validators.py
ndd_tools/welcome.py
ndd_tools-1.2.6.dist-info/METADATA
ndd_tools-1.2.6.dist-info/WHEEL
ndd_tools-1.2.6.dist-info/entry_points.txt
ndd_tools-1.2.6.dist-info/top_level.txt
ndd_tools-1.2.6.dist-info/RECORD
