Metadata-Version: 2.1
Name: ndd-tools
Version: 1.2.6
Summary: My Collection of Tools
Home-page: https://github.com/hpduongducnhan/ndd_tools
Author: hpduongducnhan
Author-email: hpduongducnhan@gmail.com
Maintainer: hpduongducnhan
Maintainer-email: hpduongducnhan@gmail.com
License: MIT
Download-URL: https://github.com/hpduongducnhan/ndd_tools/tarball/master
Platform: UNKNOWN
Classifier: Development Status :: 4 - Beta
Classifier: License :: OSI Approved :: MIT License
Classifier: Topic :: Software Development :: Libraries :: Python Modules
Classifier: Intended Audience :: Developers
Classifier: Programming Language :: Python :: 3
Requires-Python: <4,>=3.0.*
Requires-Dist: requests (==2.26.0)
Requires-Dist: pydantic (==1.8.2)
Requires-Dist: python-dotenv (==0.19.0)
Requires-Dist: PyYAML (==5.4.1)
Requires-Dist: python-dateutil (==2.8.2)
